<annotation>
   <folder>stopSignImages</folder>
   <filename>image038.jpg</filename>
   <path>F:\video\stopSignImages\image038.jpg</path>
   <source>
      <database>Unknow</database>
   </source>
   <size>
      <width>1632</width>
      <height>1224</height>
      <depth>3</depth>
   </size>
   <segmented>0</segmented>
   <object>
      <name>stop</name>
      <pose>Unspecified</pose>
      <truncated>0</truncated>
      <difficult>0</difficult>
      <bndbox>
         <xmin>604</xmin>
         <ymin>319</ymin>
         <xmax>743</xmax>
         <ymax>545</ymax>
      </bndbox>
   </object>
   <object>
      <name>stop</name>
      <pose>Unspecified</pose>
      <truncated>0</truncated>
      <difficult>0</difficult>
      <bndbox>
         <xmin>1451</xmin>
         <ymin>583</ymin>
         <xmax>1633</xmax>
         <ymax>1154</ymax>
      </bndbox>
   </object>
</annotation>
